[
{
"asset_id":
"1a8a341f-3656-4298-ac59-2fc5c2e69418",
"metadata":
{
"access":
[
{
"status":
"dandi:Open"
}
],
"blobDateModified":
"2020-10-21T20:53:22.375418-04:00",
"contentSize":
24916614016,
"dateModified":
"2021-04-21T05:45:37.506462-04:00",
"digest":
{
"dandi:dandi-etag":
"5f3c16ca28cd697fde055f42a34ff83d-372"
},
"path":
"sub-c1/sub-c1_ecephys.nwb",
"repository":
"https://dandiarchive.org/",
"schemaVersion":
"0.3.0",
"wasGeneratedBy":
[
{
"description":
"Metadata generated by DANDI cli",
"id":
"urn:uuid:98aacdfb-d0c0-48bd-b809-6c05aea7f17c",
"name":
"Metadata generation",
"schemaKey":
"Activity",
"wasAssociatedWith":
[
{
"identifier":
"RRID:SCR_019009",
"name":
"DANDI Command Line Interface",
"schemaKey":
"Software",
"url":
"https://github.com/dandi/dandi-cli",
"version":
"0.14.1+4.g350843c"
}
]
}
]
},
"modified":
"2021-05-18T13:13:56.324166+00:00",
"path":
"sub-c1/sub-c1_ecephys.nwb",
"size":
24916614016
},
{
"asset_id":
"ab766bea-88f0-43de-88bc-630824d06d13",
"metadata":
{
"access":
[
{
"status":
"dandi:Open"
}
],
"blobDateModified":
"2020-10-21T20:56:02.160634-04:00",
"contentSize":
29530187056,
"dateModified":
"2021-04-21T05:45:59.470971-04:00",
"digest":
{
"dandi:dandi-etag":
"18bb1df627accb366707636a2e64705e-441"
},
"encodingFormat":
"application/x-nwb",
"path":
"sub-MEAREC-250neuron-Neuropixels/sub-MEAREC-250neuron-Neuropixels_ecephys.nwb",
"repository":
"https://dandiarchive.org/",
"schemaVersion":
"0.3.0",
"wasAttributedTo":
[
{
"identifier":
"MEAREC_250neuron_Neuropixels",
"schemaKey":
"Participant"
}
],
"wasGeneratedBy":
[
{
"identifier":
"8f43bf0f-edb0-45cc-93eb-9acad8f2a84c",
"schemaKey":
"Session"
},
{
"description":
"Metadata generated by DANDI cli",
"id":
"urn:uuid:031fac30-9c6f-4dc7-81e3-6fded0f4de6a",
"name":
"Metadata generation",
"schemaKey":
"Activity",
"wasAssociatedWith":
[
{
"identifier":
"RRID:SCR_019009",
"name":
"DANDI Command Line Interface",
"schemaKey":
"Software",
"url":
"https://github.com/dandi/dandi-cli",
"version":
"0.14.1+4.g350843c"
}
]
}
]
},
"modified":
"2021-05-18T13:13:56.332696+00:00",
"path":
"sub-MEAREC-250neuron-Neuropixels/sub-MEAREC-250neuron-Neuropixels_ecephys.nwb",
"size":
29530187056
},
{
"asset_id":
"af1745f6-e14a-473a-987d-cef7e29a3956",
"metadata":
{
"@context":
"https://raw.githubusercontent.com/dandi/schema/master/releases/0.4.4/context.json",
"access":
[
{
"schemaKey":
"AccessRequirements",
"status":
"dandi:OpenAccess"
}
],
"approach":
[
{
"name":
"electrophysiological approach",
"schemaKey":
"ApproachType"
}
],
"blobDateModified":
"2020-10-21T21:01:16.911027-04:00",
"contentSize":
9693752,
"contentUrl":
[
"https://api.dandiarchive.org/api/assets/af1745f6-e14a-473a-987d-cef7e29a3956/download/",
"https://dandiarchive.s3.amazonaws.com/blobs/cc3/375/cc3375e3-9eb5-41d8-9992-46ffeaf4d604"
],
"dateModified":
"2021-07-02T17:25:34.772327-04:00",
"digest":
{
"dandi:dandi-etag":
"8a0b6c819c957adbbff03b6e23ea42bc-1",
"dandi:sha2-256":
"c921874e73b63e24b7a26a3dabd3d7c05fcd7e521882848c7b7b524926acc285"
},
"encodingFormat":
"application/x-nwb",
"id":
"dandiasset:af1745f6-e14a-473a-987d-cef7e29a3956",
"identifier":
"af1745f6-e14a-473a-987d-cef7e29a3956",
"measurementTechnique":
[
{
"name":
"spike sorting technique",
"schemaKey":
"MeasurementTechniqueType"
}
],
"path":
"sub-mouse412804/sub-mouse412804_ses-20200824T155542.nwb",
"repository":
"https://dandiarchive.org/",
"schemaKey":
"Asset",
"schemaVersion":
"0.4.4",
"variableMeasured":
[
{
"schemaKey":
"PropertyValue",
"value":
"Units"
}
],
"wasAttributedTo":
[
{
"identifier":
"mouse412804",
"schemaKey":
"Participant",
"species":
{
"identifier":
"http://purl.obolibrary.org/obo/NCBITaxon_10090",
"name":
"House mouse",
"schemaKey":
"SpeciesType"
}
}
],
"wasGeneratedBy":
[
{
"description":
"Metadata generated by DANDI cli",
"id":
"urn:uuid:85e44629-89a0-4d37-ac14-0a6abf5ea173",
"name":
"Metadata generation",
"schemaKey":
"Activity",
"wasAssociatedWith":
[
{
"identifier":
"RRID:SCR_019009",
"name":
"DANDI Command Line Interface",
"schemaKey":
"Software",
"url":
"https://github.com/dandi/dandi-cli",
"version":
"0.22.0"
}
]
}
]
},
"modified":
"2021-07-02T21:25:34.917274+00:00",
"path":
"sub-mouse412804/sub-mouse412804_ses-20200824T155542.nwb",
"size":
9693752
},
{
"asset_id":
"c696fc2b-d2e6-4e27-8775-01657193c4a2",
"metadata":
{
"@context":
"https://raw.githubusercontent.com/dandi/schema/master/releases/0.4.4/context.json",
"access":
[
{
"schemaKey":
"AccessRequirements",
"status":
"dandi:OpenAccess"
}
],
"approach":
[
{
"name":
"electrophysiological approach",
"schemaKey":
"ApproachType"
}
],
"blobDateModified":
"2020-10-21T21:01:17.759034-04:00",
"contentSize":
11732540,
"contentUrl":
[
"https://api.dandiarchive.org/api/assets/c696fc2b-d2e6-4e27-8775-01657193c4a2/download/",
"https://dandiarchive.s3.amazonaws.com/blobs/14f/8b2/14f8b27a-e387-44f1-80e4-da76767bdc95"
],
"dateModified":
"2021-07-02T17:25:35.041358-04:00",
"digest":
{
"dandi:dandi-etag":
"a3410890fd8ec79f9d9d0d6035fd106d-1",
"dandi:sha2-256":
"9480853d14c4ca3e0afa7389a4c4315c405b0e4758f9c8e25faeb8dab408395e"
},
"encodingFormat":
"application/x-nwb",
"id":
"dandiasset:c696fc2b-d2e6-4e27-8775-01657193c4a2",
"identifier":
"c696fc2b-d2e6-4e27-8775-01657193c4a2",
"measurementTechnique":
[
{
"name":
"spike sorting technique",
"schemaKey":
"MeasurementTechniqueType"
}
],
"path":
"sub-mouse412804/sub-mouse412804_ses-20200824T155543.nwb",
"repository":
"https://dandiarchive.org/",
"schemaKey":
"Asset",
"schemaVersion":
"0.4.4",
"variableMeasured":
[
{
"schemaKey":
"PropertyValue",
"value":
"Units"
}
],
"wasAttributedTo":
[
{
"identifier":
"mouse412804",
"schemaKey":
"Participant",
"species":
{
"identifier":
"http://purl.obolibrary.org/obo/NCBITaxon_10090",
"name":
"House mouse",
"schemaKey":
"SpeciesType"
}
}
],
"wasGeneratedBy":
[
{
"description":
"Metadata generated by DANDI cli",
"id":
"urn:uuid:44d13e26-3104-4c94-9dc6-f25aea676583",
"name":
"Metadata generation",
"schemaKey":
"Activity",
"wasAssociatedWith":
[
{
"identifier":
"RRID:SCR_019009",
"name":
"DANDI Command Line Interface",
"schemaKey":
"Software",
"url":
"https://github.com/dandi/dandi-cli",
"version":
"0.22.0"
}
]
}
]
},
"modified":
"2021-07-02T21:25:35.172198+00:00",
"path":
"sub-mouse412804/sub-mouse412804_ses-20200824T155543.nwb",
"size":
11732540
},
{
"asset_id":
"9822a813-0dec-4d07-810b-1c13341c168d",
"metadata":
{
"@context":
"https://raw.githubusercontent.com/dandi/schema/master/releases/0.4.4/context.json",
"access":
[
{
"schemaKey":
"AccessRequirements",
"status":
"dandi:OpenAccess"
}
],
"approach":
[
{
"name":
"electrophysiological approach",
"schemaKey":
"ApproachType"
}
],
"blobDateModified":
"2020-10-21T21:01:21.275061-04:00",
"contentSize":
6470908640,
"contentUrl":
[
"https://api.dandiarchive.org/api/assets/9822a813-0dec-4d07-810b-1c13341c168d/download/",
"https://dandiarchive.s3.amazonaws.com/blobs/5b1/a6e/5b1a6ecf-b2b0-4355-8535-6ba9c70bbe03"
],
"dateModified":
"2021-07-02T17:25:35.424820-04:00",
"digest":
{
"dandi:dandi-etag":
"06bbde074588c3c1802aa41b7778fe79-97",
"dandi:sha2-256":
"a7789cf7a3cc8359133aadb8a3936bc12650491af393968ee2e9af1eff3f6790"
},
"encodingFormat":
"application/x-nwb",
"id":
"dandiasset:9822a813-0dec-4d07-810b-1c13341c168d",
"identifier":
"9822a813-0dec-4d07-810b-1c13341c168d",
"measurementTechnique":
[
{
"name":
"surgical technique",
"schemaKey":
"MeasurementTechniqueType"
},
{
"name":
"multi electrode extracellular electrophysiology recording technique",
"schemaKey":
"MeasurementTechniqueType"
}
],
"path":
"sub-P29-16-05-14-retina02-left/sub-P29-16-05-14-retina02-left_ecephys.nwb",
"repository":
"https://dandiarchive.org/",
"schemaKey":
"Asset",
"schemaVersion":
"0.4.4",
"variableMeasured":
[
{
"schemaKey":
"PropertyValue",
"value":
"ElectrodeGroup"
},
{
"schemaKey":
"PropertyValue",
"value":
"ElectricalSeries"
}
],
"wasAttributedTo":
[
{
"identifier":
"P29_16_05_14_retina02_left",
"schemaKey":
"Participant",
"species":
{
"identifier":
"http://purl.obolibrary.org/obo/NCBITaxon_10090",
"name":
"House mouse",
"schemaKey":
"SpeciesType"
}
}
],
"wasGeneratedBy":
[
{
"description":
"Metadata generated by DANDI cli",
"id":
"urn:uuid:ffd50394-41f0-4249-9bb5-098cbba1e601",
"name":
"Metadata generation",
"schemaKey":
"Activity",
"wasAssociatedWith":
[
{
"identifier":
"RRID:SCR_019009",
"name":
"DANDI Command Line Interface",
"schemaKey":
"Software",
"url":
"https://github.com/dandi/dandi-cli",
"version":
"0.22.0"
}
]
}
]
},
"modified":
"2021-07-02T21:25:35.565942+00:00",
"path":
"sub-P29-16-05-14-retina02-left/sub-P29-16-05-14-retina02-left_ecephys.nwb",
"size":
6470908640
},
{
"asset_id":
"3e0d4539-902e-46b4-9cfb-119e0f69fbd0",
"metadata":
{
"@context":
"https://raw.githubusercontent.com/dandi/schema/master/releases/0.4.4/context.json",
"access":
[
{
"schemaKey":
"AccessRequirements",
"status":
"dandi:OpenAccess"
}
],
"approach":
[
{
"name":
"electrophysiological approach",
"schemaKey":
"ApproachType"
}
],
"blobDateModified":
"2020-10-21T20:59:33.834244-04:00",
"contentSize":
13411878072,
"contentUrl":
[
"https://api.dandiarchive.org/api/assets/3e0d4539-902e-46b4-9cfb-119e0f69fbd0/download/",
"https://dandiarchive.s3.amazonaws.com/blobs/df5/73d/df573dcc-1a95-4845-b276-6ccc24fb2f49"
],
"dateModified":
"2021-07-02T17:25:35.553795-04:00",
"digest":
{
"dandi:dandi-etag":
"449be0940b60d575538a05968d08b758-200",
"dandi:sha2-256":
"b6573d4d829a709e79ed39f31ab64405d849f9ad2dfd2510ae50157e1c25286c"
},
"encodingFormat":
"application/x-nwb",
"id":
"dandiasset:3e0d4539-902e-46b4-9cfb-119e0f69fbd0",
"identifier":
"3e0d4539-902e-46b4-9cfb-119e0f69fbd0",
"measurementTechnique":
[
{
"name":
"surgical technique",
"schemaKey":
"MeasurementTechniqueType"
},
{
"name":
"multi electrode extracellular electrophysiology recording technique",
"schemaKey":
"MeasurementTechniqueType"
}
],
"path":
"sub-mouse412804/sub-mouse412804_ecephys.nwb",
"repository":
"https://dandiarchive.org/",
"schemaKey":
"Asset",
"schemaVersion":
"0.4.4",
"variableMeasured":
[
{
"schemaKey":
"PropertyValue",
"value":
"ElectrodeGroup"
},
{
"schemaKey":
"PropertyValue",
"value":
"ElectricalSeries"
}
],
"wasAttributedTo":
[
{
"identifier":
"mouse412804",
"schemaKey":
"Participant",
"species":
{
"identifier":
"http://purl.obolibrary.org/obo/NCBITaxon_10090",
"name":
"House mouse",
"schemaKey":
"SpeciesType"
}
}
],
"wasGeneratedBy":
[
{
"description":
"Metadata generated by DANDI cli",
"id":
"urn:uuid:8f27ca1d-7f07-4155-bad6-87073e437c87",
"name":
"Metadata generation",
"schemaKey":
"Activity",
"wasAssociatedWith":
[
{
"identifier":
"RRID:SCR_019009",
"name":
"DANDI Command Line Interface",
"schemaKey":
"Software",
"url":
"https://github.com/dandi/dandi-cli",
"version":
"0.22.0"
}
]
}
]
},
"modified":
"2021-07-02T21:25:35.707241+00:00",
"path":
"sub-mouse412804/sub-mouse412804_ecephys.nwb",
"size":
13411878072
}
]